library.policy-2.0.6-py3.12-nspkg.pth
library/policy/__init__.py
library/policy/configure.zcml
library/policy/interfaces.py
library/policy/permissions.zcml
library/policy/setuphandlers.py
library/policy/testing.py
library/policy/utils.py
library/policy/browser/__init__.py
library/policy/browser/configure.zcml
library/policy/browser/overrides/.gitkeep
library/policy/browser/static/.gitkeep
library/policy/faceted/__init__.py
library/policy/faceted/configure.zcml
library/policy/faceted/explorer.py
library/policy/faceted/config/explorer.xml
library/policy/faceted/config/periodes.xml
library/policy/faceted/templates/explorer.pt
library/policy/locales/library.policy.pot
library/policy/locales/update.sh
library/policy/locales/fr/LC_MESSAGES/library.policy.po
library/policy/profiles/default/browserlayer.xml
library/policy/profiles/default/catalog.xml
library/policy/profiles/default/metadata.xml
library/policy/profiles/default/registry.xml
library/policy/profiles/default/rolemap.xml
library/policy/profiles/default/types.xml
library/policy/profiles/default/viewlets.xml
library/policy/profiles/default/taxonomies/dossiers.cfg
library/policy/profiles/default/taxonomies/dossiers.xml
library/policy/profiles/default/taxonomies/periodes.cfg
library/policy/profiles/default/taxonomies/periodes.xml
library/policy/profiles/default/taxonomies/types_de_patrimoine.cfg
library/policy/profiles/default/taxonomies/types_de_patrimoine.xml
library/policy/profiles/default/taxonomies/villages.cfg
library/policy/profiles/default/taxonomies/villages.xml
library/policy/profiles/default/types/Document.xml
library/policy/profiles/default/types/Folder.xml
library/policy/profiles/uninstall/browserlayer.xml
library/policy/tests/__init__.py
library/policy/tests/test_robot.py
library/policy/tests/test_setup.py
library/policy/tests/robot/test_example.robot
library/policy/upgrades/__init__.py
library/policy/upgrades/configure.zcml
library/policy/upgrades/upgrades.py
library_policy-2.0.6.dist-info/licenses/LICENSE.GPL
library_policy-2.0.6.dist-info/licenses/LICENSE.rst
library_policy-2.0.6.dist-info/METADATA
library_policy-2.0.6.dist-info/WHEEL
library_policy-2.0.6.dist-info/namespace_packages.txt
library_policy-2.0.6.dist-info/top_level.txt
library_policy-2.0.6.dist-info/RECORD
