Metadata-Version: 2.4
Name: library.policy
Version: 2.0.6
Summary: Policy for the installation of buildout.library
Home-page: https://pypi.python.org/pypi/library.policy
Author: Nicolas Demonte
Author-email: support@imio.be
License: GPL version 2
Keywords: Python Plone
Classifier: Environment :: Web Environment
Classifier: Framework :: Plone
Classifier: Framework :: Plone :: 6.0
Classifier: Framework :: Plone :: Addon
Classifier: Programming Language :: Python
Classifier: Programming Language :: Python :: 3.8
Classifier: Programming Language :: Python :: 3.9
Classifier: Programming Language :: Python :: 3.10
Classifier: Operating System :: OS Independent
Classifier: License :: OSI Approved :: GNU General Public License v2 (GPLv2)
License-File: LICENSE.GPL
License-File: LICENSE.rst
Requires-Dist: plone.api>=1.8.4
Requires-Dist: Products.GenericSetup>=1.8.2
Requires-Dist: setuptools
Requires-Dist: z3c.jbot
Requires-Dist: eea.facetednavigation
Requires-Dist: eea.jquery
Requires-Dist: collective.big.bang
Requires-Dist: collective.faceted.map
Requires-Dist: collective.faceted.taxonomywidget
Requires-Dist: collective.js.jqueryui
Requires-Dist: collective.taxonomy
Requires-Dist: plone.app.imagecropping
Requires-Dist: plone.app.mosaic
Requires-Dist: plone.app.theming
Requires-Dist: plone.app.themingplugins
Requires-Dist: library.core
Requires-Dist: collective.behavior.banner
Requires-Dist: collective.behavior.gallery
Requires-Dist: collective.easyform
Requires-Dist: collective.preventactions
Requires-Dist: collective.cookiecuttr
Requires-Dist: iaweb.mosaic
Requires-Dist: collective.plausible
Requires-Dist: plone.formwidget.recaptcha
Provides-Extra: test
Requires-Dist: plone.app.testing; extra == "test"
Requires-Dist: plone.testing>=5.0.0; extra == "test"
Requires-Dist: plone.app.contenttypes; extra == "test"
Requires-Dist: plone.app.robotframework[debug]; extra == "test"
Dynamic: author
Dynamic: author-email
Dynamic: classifier
Dynamic: description
Dynamic: home-page
Dynamic: keywords
Dynamic: license
Dynamic: license-file
Dynamic: provides-extra
Dynamic: requires-dist
Dynamic: summary
